whut/__init__.py
whut/cli.py
whut-0.7.2.dist-info/LICENSE
whut-0.7.2.dist-info/METADATA
whut-0.7.2.dist-info/WHEEL
whut-0.7.2.dist-info/entry_points.txt
whut-0.7.2.dist-info/top_level.txt
whut-0.7.2.dist-info/RECORD
